[
  {
    "image": "output/processed_images\\page10_image1.jpeg",
    "generated_question": "what question does this image represent?"
  },
  {
    "image": "output/processed_images\\page10_image2.png",
    "generated_question": "what question does this image represent?"
  },
  {
    "image": "output/processed_images\\page10_image3.png",
    "generated_question": "what question does this image represent?"
  },
  {
    "image": "output/processed_images\\page10_image4.png",
    "generated_question": "what question does this image represent?"
  },
  {
    "image": "output/processed_images\\page11_image1.jpeg",
    "generated_question": "what question does this image represent?"
  },
  {
    "image": "output/processed_images\\page11_image2.png",
    "generated_question": "what question does this image represent?"
  },
  {
    "image": "output/processed_images\\page11_image3.png",
    "generated_question": "what question does this image represent?"
  },
  {
    "image": "output/processed_images\\page11_image4.jpeg",
    "generated_question": "what question does this image represent?"
  },
  {
    "image": "output/processed_images\\page12_image1.jpeg",
    "generated_question": "what question does this image represent?"
  },
  {
    "image": "output/processed_images\\page12_image2.png",
    "generated_question": "what question does this image represent?"
  },
  {
    "image": "output/processed_images\\page13_image1.jpeg",
    "generated_question": "what question does this image represent?"
  },
  {
    "image": "output/processed_images\\page13_image2.png",
    "generated_question": "what question does this image represent?"
  },
  {
    "image": "output/processed_images\\page13_image3.png",
    "generated_question": "what question does this image represent?"
  },
  {
    "image": "output/processed_images\\page14_image1.jpeg",
    "generated_question": "what question does this image represent?"
  },
  {
    "image": "output/processed_images\\page1_image1.jpeg",
    "generated_question": "what question does this image represent?"
  },
  {
    "image": "output/processed_images\\page1_image10.png",
    "generated_question": "what question does this image represent?"
  },
  {
    "image": "output/processed_images\\page1_image2.png",
    "generated_question": "what question does this image represent?"
  },
  {
    "image": "output/processed_images\\page1_image3.png",
    "generated_question": "what question does this image represent?"
  },
  {
    "image": "output/processed_images\\page1_image4.png",
    "generated_question": "what question does this image represent?"
  },
  {
    "image": "output/processed_images\\page1_image5.png",
    "generated_question": "what question does this image represent?"
  },
  {
    "image": "output/processed_images\\page1_image6.png",
    "generated_question": "what question does this image represent?"
  },
  {
    "image": "output/processed_images\\page1_image7.png",
    "generated_question": "what question does this image represent?"
  },
  {
    "image": "output/processed_images\\page1_image8.png",
    "generated_question": "what question does this image represent?"
  },
  {
    "image": "output/processed_images\\page1_image9.png",
    "generated_question": "what question does this image represent?"
  },
  {
    "image": "output/processed_images\\page2_image1.jpeg",
    "generated_question": "what question does this image represent?"
  },
  {
    "image": "output/processed_images\\page2_image2.png",
    "generated_question": "what question does this image represent?"
  },
  {
    "image": "output/processed_images\\page2_image3.png",
    "generated_question": "what question does this image represent?"
  },
  {
    "image": "output/processed_images\\page2_image4.png",
    "generated_question": "what question does this image represent?"
  },
  {
    "image": "output/processed_images\\page2_image5.png",
    "generated_question": "what question does this image represent?"
  },
  {
    "image": "output/processed_images\\page2_image6.jpeg",
    "generated_question": "what question does this image represent?"
  },
  {
    "image": "output/processed_images\\page2_image7.png",
    "generated_question": "what question does this image represent?"
  },
  {
    "image": "output/processed_images\\page3_image1.jpeg",
    "generated_question": "what question does this image represent?"
  },
  {
    "image": "output/processed_images\\page3_image2.png",
    "generated_question": "what question does this image represent?"
  },
  {
    "image": "output/processed_images\\page4_image1.jpeg",
    "generated_question": "what question does this image represent?"
  },
  {
    "image": "output/processed_images\\page4_image2.jpeg",
    "generated_question": "what question does this image represent?"
  },
  {
    "image": "output/processed_images\\page4_image3.png",
    "generated_question": "what question does this image represent?"
  },
  {
    "image": "output/processed_images\\page4_image4.png",
    "generated_question": "what question does this image represent?"
  },
  {
    "image": "output/processed_images\\page4_image5.png",
    "generated_question": "what question does this image represent?"
  },
  {
    "image": "output/processed_images\\page5_image1.jpeg",
    "generated_question": "what question does this image represent?"
  },
  {
    "image": "output/processed_images\\page5_image2.png",
    "generated_question": "what question does this image represent?"
  },
  {
    "image": "output/processed_images\\page5_image3.png",
    "generated_question": "what question does this image represent?"
  },
  {
    "image": "output/processed_images\\page5_image4.png",
    "generated_question": "what question does this image represent?"
  },
  {
    "image": "output/processed_images\\page5_image5.png",
    "generated_question": "what question does this image represent?"
  },
  {
    "image": "output/processed_images\\page6_image1.jpeg",
    "generated_question": "what question does this image represent?"
  },
  {
    "image": "output/processed_images\\page6_image2.png",
    "generated_question": "what question does this image represent?"
  },
  {
    "image": "output/processed_images\\page6_image3.png",
    "generated_question": "what question does this image represent?"
  },
  {
    "image": "output/processed_images\\page7_image1.jpeg",
    "generated_question": "what question does this image represent?"
  },
  {
    "image": "output/processed_images\\page8_image1.jpeg",
    "generated_question": "what question does this image represent?"
  },
  {
    "image": "output/processed_images\\page8_image2.jpeg",
    "generated_question": "what question does this image represent?"
  },
  {
    "image": "output/processed_images\\page8_image3.jpeg",
    "generated_question": "what question does this image represent?"
  },
  {
    "image": "output/processed_images\\page8_image4.jpeg",
    "generated_question": "what question does this image represent?"
  },
  {
    "image": "output/processed_images\\page8_image5.jpeg",
    "generated_question": "what question does this image represent?"
  },
  {
    "image": "output/processed_images\\page8_image6.png",
    "generated_question": "what question does this image represent?"
  },
  {
    "image": "output/processed_images\\page8_image7.png",
    "generated_question": "what question does this image represent?"
  },
  {
    "image": "output/processed_images\\page8_image8.png",
    "generated_question": "what question does this image represent?"
  },
  {
    "image": "output/processed_images\\page8_image9.png",
    "generated_question": "what question does this image represent?"
  },
  {
    "image": "output/processed_images\\page9_image1.jpeg",
    "generated_question": "what question does this image represent?"
  },
  {
    "image": "output/processed_images\\page9_image2.png",
    "generated_question": "what question does this image represent?"
  },
  {
    "image": "output/processed_images\\page9_image3.png",
    "generated_question": "what question does this image represent?"
  },
  {
    "image": "output/processed_images\\page9_image4.png",
    "generated_question": "what question does this image represent?"
  },
  {
    "image": "output/processed_images\\page9_image5.png",
    "generated_question": "what question does this image represent?"
  },
  {
    "image": "output/processed_images\\page9_image6.png",
    "generated_question": "what question does this image represent?"
  }
]